{
  "project_info": {
    "project_number": "48282727524",
    "project_id": "learnopus",
    "storage_bucket": "learnopus.appspot.com"
  },
  "client": [
    {
      "client_info": {
        "mobilesdk_app_id": "1:48282727524:android:4c4ac7cab91c7cc41f5b71",
        "android_client_info": {
          "package_name": "com.example.learnopus"
        }
      },
      "oauth_client": [
        {
          "client_id": "48282727524-f4l1rjhl1ufo85u5mdfpc3hig1j8kanm.apps.googleusercontent.com",
          "client_type": 1,
          "android_info": {
            "package_name": "com.example.learnopus",
            "certificate_hash": "2d152cd12b784f0718b22a5b786e4ec36c128452"
          }
        },
        {
          "client_id": "48282727524-1bue1di424imffg9mflj0mnchttm22tj.apps.googleusercontent.com",
          "client_type": 3
        }
      ],
      "api_key": [
        {
          "current_key": "AIzaSyBvihh3yAdhL1xN5nxG_2hci6xJ2o0zCL8"
        }
      ],
      "services": {
        "appinvite_service": {
          "other_platform_oauth_client": [
            {
              "client_id": "48282727524-1bue1di424imffg9mflj0mnchttm22tj.apps.googleusercontent.com",
              "client_type": 3
            }
          ]
        }
      }
    }
  ],
  "configuration_version": "1"
}